root_painter/__init__.py
root_painter/about.py
root_painter/assign_corrections.py
root_painter/base_extract.py
root_painter/controls_dialog.py
root_painter/convert_seg.py
root_painter/create_dataset.py
root_painter/create_project.py
root_painter/eccentricity.py
root_painter/extract_comp.py
root_painter/extract_count.py
root_painter/extract_length.py
root_painter/extract_regions.py
root_painter/file_utils.py
root_painter/graphics_scene.py
root_painter/graphics_view.py
root_painter/im_utils.py
root_painter/im_viewer.py
root_painter/instructions.py
root_painter/interaction_time.py
root_painter/main.py
root_painter/mask_images.py
root_painter/name_edit_widget.py
root_painter/nav.py
root_painter/palette.py
root_painter/plot_seg_metrics.py
root_painter/progress_widget.py
root_painter/random_split.py
root_painter/resize_images.py
root_painter/root_painter.py
root_painter/segment_folder.py
root_painter/visibility_widget.py
root_painter/icons/Icon.icns
root_painter/icons/Icon.ico
root_painter/icons/create_icns.sh
root_painter/icons/icon.svg
root_painter/icons/icons.md
root_painter/icons/base/16.png
root_painter/icons/base/24.png
root_painter/icons/base/32.png
root_painter/icons/base/48.png
root_painter/icons/base/64.png
root_painter/icons/linux/1024.png
root_painter/icons/linux/128.png
root_painter/icons/linux/256.png
root_painter/icons/linux/512.png
root_painter/icons/mac/1024.png
root_painter/icons/mac/128.png
root_painter/icons/mac/256.png
root_painter/icons/mac/512.png
root_painter_painter-0.1.1.dist-info/METADATA
root_painter_painter-0.1.1.dist-info/WHEEL
root_painter_painter-0.1.1.dist-info/RECORD
